pgcopylib/__init__.py
pgcopylib/reader.py
pgcopylib/writer.py
pgcopylib/common/__init__.py
pgcopylib/common/base.cpython-310-x86_64-linux-gnu.so
pgcopylib/common/base.pxd
pgcopylib/common/base.pyi
pgcopylib/common/base.pyx
pgcopylib/common/buffer_object.py
pgcopylib/common/enums.py
pgcopylib/common/errors.py
pgcopylib/common/dtypes/__init__.py
pgcopylib/common/dtypes/dtype.py
pgcopylib/common/dtypes/functions/__init__.py
pgcopylib/common/dtypes/functions/arrays.cpython-310-x86_64-linux-gnu.so
pgcopylib/common/dtypes/functions/arrays.pxd
pgcopylib/common/dtypes/functions/arrays.pyi
pgcopylib/common/dtypes/functions/arrays.pyx
pgcopylib/common/dtypes/functions/dates.cpython-310-x86_64-linux-gnu.so
pgcopylib/common/dtypes/functions/dates.pxd
pgcopylib/common/dtypes/functions/dates.pyi
pgcopylib/common/dtypes/functions/dates.pyx
pgcopylib/common/dtypes/functions/digits.cpython-310-x86_64-linux-gnu.so
pgcopylib/common/dtypes/functions/digits.pxd
pgcopylib/common/dtypes/functions/digits.pyi
pgcopylib/common/dtypes/functions/digits.pyx
pgcopylib/common/dtypes/functions/geometrics.cpython-310-x86_64-linux-gnu.so
pgcopylib/common/dtypes/functions/geometrics.pxd
pgcopylib/common/dtypes/functions/geometrics.pyi
pgcopylib/common/dtypes/functions/geometrics.pyx
pgcopylib/common/dtypes/functions/ipaddrs.cpython-310-x86_64-linux-gnu.so
pgcopylib/common/dtypes/functions/ipaddrs.pxd
pgcopylib/common/dtypes/functions/ipaddrs.pyi
pgcopylib/common/dtypes/functions/ipaddrs.pyx
pgcopylib/common/dtypes/functions/jsons.cpython-310-x86_64-linux-gnu.so
pgcopylib/common/dtypes/functions/jsons.pxd
pgcopylib/common/dtypes/functions/jsons.pyi
pgcopylib/common/dtypes/functions/jsons.pyx
pgcopylib/common/dtypes/functions/strings.cpython-310-x86_64-linux-gnu.so
pgcopylib/common/dtypes/functions/strings.pxd
pgcopylib/common/dtypes/functions/strings.pyi
pgcopylib/common/dtypes/functions/strings.pyx
pgcopylib-0.2.3.2.dist-info/METADATA
pgcopylib-0.2.3.2.dist-info/WHEEL
pgcopylib-0.2.3.2.dist-info/top_level.txt
pgcopylib-0.2.3.2.dist-info/RECORD
pgcopylib-0.2.3.2.dist-info/licenses/LICENSE
