Metadata-Version: 2.4
Name: pgcopylib
Version: 0.2.3.2
Summary: PGCopy bynary dump parser.
Author-email: 0xMihalich <bayanmobile87@gmail.com>
License: MIT License
Project-URL: Homepage, https://github.com/0xMihalich/pgcopylib
Project-URL: Documentation, https://github.com/0xMihalich/pgcopylib#readme
Project-URL: Repository, https://github.com/0xMihalich/pgcopylib
Project-URL: Changelog, https://github.com/0xMihalich/pgcopylib/blob/main/CHANGELOG.md
Classifier: Development Status :: 4 - Beta
Classifier: Intended Audience :: Developers
Classifier: Programming Language :: Python :: 3.10
Classifier: Programming Language :: Python :: 3.11
Classifier: Programming Language :: Python :: 3.12
Classifier: Programming Language :: Python :: 3.13
Classifier: Programming Language :: Python :: 3.14
Requires-Python: >=3.10
License-File: LICENSE
Dynamic: license-file
